webng/__init__.py
webng/main.py
webng/analysis/__init__.py
webng/analysis/analysis.py
webng/analysis/average.py
webng/analysis/cluster.py
webng/analysis/evolution.py
webng/analysis/network.py
webng/analysis/utils.py
webng/controllers/__init__.py
webng/controllers/base.py
webng/core/__init__.py
webng/core/exc.py
webng/core/version.py
webng/core/weAnalysis.py
webng/core/weConvert.py
webng/core/weTemplater.py
webng-0.0.8.dist-info/LICENSE.md
webng-0.0.8.dist-info/METADATA
webng-0.0.8.dist-info/WHEEL
webng-0.0.8.dist-info/entry_points.txt
webng-0.0.8.dist-info/top_level.txt
webng-0.0.8.dist-info/RECORD
