Metadata-Version: 2.1
Name: webng
Version: 0.0.8
Summary: A weighted ensemble simulation setup tool starting from a BNGL model
Home-page: https://github.com/ASinanSaglam/BNG_WESTPA_pipeline
Author: Ali Sinan Saglam
Author-email: asinansaglam@gmail.com
License: unlicensed
Platform: UNKNOWN
License-File: LICENSE.md
